[
  {
    "id": "mia",
    "name": "Mia",
    "breed": "Rottweiler",
    "sex": "F",
    "dob": "2020-01-15",
    "weight_kg": "~45",
    "microchip": "",
    "council_reg": "",
    "last_vet": "",
    "notes": "First litter; calm attentive mum."
  },
  {
    "id": "thor",
    "name": "Thor",
    "breed": "Cane Corso",
    "sex": "M",
    "dob": "2023-07-10",
    "weight_kg": "~45",
    "microchip": "",
    "council_reg": "74582 (City of Melton)",
    "last_vet": "2025-07-10 desexed",
    "notes": "Sire; desexed Jul 2025."
  }
]